[
  {
    "oldid": 3537,
    "summary": "RainbowBatch update",
    "time": {
      "date": 1662076800000,
      "day": 2,
      "hour": 4,
      "microsecond": 0,
      "month": 9,
      "second": 6,
      "timezone": "UTC",
      "weekday": 5
    },
    "username": "RainbowBatch"
  },
  {
    "oldid": 3477,
    "summary": "RainbowBatch update",
    "time": {
      "date": 1661817600000,
      "day": 30,
      "hour": 20,
      "microsecond": 0,
      "month": 8,
      "second": 59,
      "timezone": "UTC",
      "weekday": 2
    },
    "username": "RainbowBatch"
  },
  {
    "oldid": 2724,
    "summary": "RainbowBatch generated stub.",
    "time": {
      "date": 1661731200000,
      "day": 29,
      "hour": 4,
      "microsecond": 0,
      "month": 8,
      "second": 54,
      "timezone": "UTC",
      "weekday": 1
    },
    "username": "RainbowBatch"
  }
]