[
  {
    "oldid": 3928,
    "summary": "RainbowBatch update",
    "time": {
      "date": 1664668800000,
      "day": 2,
      "hour": 1,
      "microsecond": 0,
      "month": 10,
      "second": 56,
      "timezone": "UTC",
      "weekday": 7
    },
    "username": "RainbowBatch"
  },
  {
    "oldid": 3926,
    "summary": "RainbowBatch update",
    "time": {
      "date": 1664668800000,
      "day": 2,
      "hour": 1,
      "microsecond": 0,
      "month": 10,
      "second": 26,
      "timezone": "UTC",
      "weekday": 7
    },
    "username": "RainbowBatch"
  },
  {
    "oldid": 3895,
    "summary": "Add ooc drop",
    "time": {
      "date": 1664496000000,
      "day": 30,
      "hour": 22,
      "microsecond": 0,
      "month": 9,
      "second": 57,
      "timezone": "UTC",
      "weekday": 5
    },
    "username": "Woursler"
  },
  {
    "oldid": 3894,
    "summary": "Try out adding tidbits from otter...",
    "time": {
      "date": 1664496000000,
      "day": 30,
      "hour": 22,
      "microsecond": 0,
      "month": 9,
      "second": 57,
      "timezone": "UTC",
      "weekday": 5
    },
    "username": "Woursler"
  },
  {
    "oldid": 3890,
    "summary": "RainbowBatch generated stub.",
    "time": {
      "date": 1664496000000,
      "day": 30,
      "hour": 11,
      "microsecond": 0,
      "month": 9,
      "second": 27,
      "timezone": "UTC",
      "weekday": 5
    },
    "username": "RainbowBatch"
  }
]