[
  {
    "oldid": 12853,
    "summary": "RainbowBatch update",
    "time": {
      "date": 1683244800000,
      "day": 5,
      "hour": 6,
      "microsecond": 0,
      "month": 5,
      "second": 49,
      "timezone": "UTC",
      "weekday": 5
    },
    "username": "RainbowBatch"
  },
  {
    "oldid": 12808,
    "summary": "RainbowBatch generated stub.",
    "time": {
      "date": 1683158400000,
      "day": 4,
      "hour": 17,
      "microsecond": 0,
      "month": 5,
      "second": 48,
      "timezone": "UTC",
      "weekday": 4
    },
    "username": "RainbowBatch"
  }
]