[
  {
    "oldid": 15543,
    "summary": "RainbowBatch update",
    "time": {
      "date": 1706313600000,
      "day": 27,
      "hour": 1,
      "microsecond": 0,
      "month": 1,
      "second": 14,
      "timezone": "UTC",
      "weekday": 6
    },
    "username": "RainbowBatch"
  },
  {
    "oldid": 13587,
    "summary": "RainbowBatch update",
    "time": {
      "date": 1694649600000,
      "day": 14,
      "hour": 2,
      "microsecond": 0,
      "month": 9,
      "second": 46,
      "timezone": "UTC",
      "weekday": 4
    },
    "username": "RainbowBatch"
  },
  {
    "oldid": 13485,
    "summary": "RainbowBatch update",
    "time": {
      "date": 1694563200000,
      "day": 13,
      "hour": 14,
      "microsecond": 0,
      "month": 9,
      "second": 55,
      "timezone": "UTC",
      "weekday": 3
    },
    "username": "RainbowBatch"
  },
  {
    "oldid": 13317,
    "summary": "RainbowBatch update",
    "time": {
      "date": 1694217600000,
      "day": 9,
      "hour": 21,
      "microsecond": 0,
      "month": 9,
      "second": 45,
      "timezone": "UTC",
      "weekday": 6
    },
    "username": "RainbowBatch"
  },
  {
    "oldid": 13315,
    "summary": "RainbowBatch generated stub.",
    "time": {
      "date": 1691280000000,
      "day": 6,
      "hour": 21,
      "microsecond": 0,
      "month": 8,
      "second": 40,
      "timezone": "UTC",
      "weekday": 7
    },
    "username": "RainbowBatch"
  }
]