[
  {
    "oldid": 537,
    "summary": "Adding categories",
    "time": {
      "date": 1658534400000,
      "day": 23,
      "hour": 22,
      "microsecond": 0,
      "month": 7,
      "second": 28,
      "timezone": "UTC",
      "weekday": 6
    },
    "username": "Tesseractor"
  },
  {
    "oldid": 536,
    "summary": "",
    "time": {
      "date": 1658534400000,
      "day": 23,
      "hour": 22,
      "microsecond": 0,
      "month": 7,
      "second": 20,
      "timezone": "UTC",
      "weekday": 6
    },
    "username": "Tesseractor"
  },
  {
    "oldid": 523,
    "summary": "Transfer the original page.",
    "time": {
      "date": 1658534400000,
      "day": 23,
      "hour": 21,
      "microsecond": 0,
      "month": 7,
      "second": 2,
      "timezone": "UTC",
      "weekday": 6
    },
    "username": "Woursler"
  }
]