[
  {
    "oldid": 505,
    "summary": "",
    "time": {
      "date": 1658534400000,
      "day": 23,
      "hour": 18,
      "microsecond": 0,
      "month": 7,
      "second": 59,
      "timezone": "UTC",
      "weekday": 6
    },
    "username": "Woursler"
  },
  {
    "oldid": 436,
    "summary": "Change link text.",
    "time": {
      "date": 1658448000000,
      "day": 22,
      "hour": 21,
      "microsecond": 0,
      "month": 7,
      "second": 57,
      "timezone": "UTC",
      "weekday": 5
    },
    "username": "Woursler"
  },
  {
    "oldid": 382,
    "summary": "Initial draft, kinda more focused on what we know from the legal case.",
    "time": {
      "date": 1658275200000,
      "day": 20,
      "hour": 20,
      "microsecond": 0,
      "month": 7,
      "second": 10,
      "timezone": "UTC",
      "weekday": 3
    },
    "username": "Woursler"
  }
]