[
  {
    "oldid": 11113,
    "summary": "RainbowBatch update",
    "time": {
      "date": 1680393600000,
      "day": 2,
      "hour": 4,
      "microsecond": 0,
      "month": 4,
      "second": 38,
      "timezone": "UTC",
      "weekday": 7
    },
    "username": "RainbowBatch"
  },
  {
    "oldid": 8510,
    "summary": "RainbowBatch update",
    "time": {
      "date": 1677196800000,
      "day": 24,
      "hour": 15,
      "microsecond": 0,
      "month": 2,
      "second": 12,
      "timezone": "UTC",
      "weekday": 5
    },
    "username": "RainbowBatch"
  },
  {
    "oldid": 8351,
    "summary": "RainbowBatch update",
    "time": {
      "date": 1676937600000,
      "day": 21,
      "hour": 21,
      "microsecond": 0,
      "month": 2,
      "second": 58,
      "timezone": "UTC",
      "weekday": 2
    },
    "username": "RainbowBatch"
  },
  {
    "oldid": 8180,
    "summary": "RainbowBatch update",
    "time": {
      "date": 1676764800000,
      "day": 19,
      "hour": 5,
      "microsecond": 0,
      "month": 2,
      "second": 38,
      "timezone": "UTC",
      "weekday": 7
    },
    "username": "RainbowBatch"
  },
  {
    "oldid": 7977,
    "summary": "RainbowBatch update",
    "time": {
      "date": 1676592000000,
      "day": 17,
      "hour": 19,
      "microsecond": 0,
      "month": 2,
      "second": 2,
      "timezone": "UTC",
      "weekday": 5
    },
    "username": "RainbowBatch"
  },
  {
    "oldid": 7781,
    "summary": "RainbowBatch update",
    "time": {
      "date": 1675987200000,
      "day": 10,
      "hour": 17,
      "microsecond": 0,
      "month": 2,
      "second": 53,
      "timezone": "UTC",
      "weekday": 5
    },
    "username": "RainbowBatch"
  },
  {
    "oldid": 7601,
    "summary": "RainbowBatch update",
    "time": {
      "date": 1675468800000,
      "day": 4,
      "hour": 7,
      "microsecond": 0,
      "month": 2,
      "second": 33,
      "timezone": "UTC",
      "weekday": 6
    },
    "username": "RainbowBatch"
  },
  {
    "oldid": 6645,
    "summary": "RainbowBatch update",
    "time": {
      "date": 1675209600000,
      "day": 1,
      "hour": 7,
      "microsecond": 0,
      "month": 2,
      "second": 11,
      "timezone": "UTC",
      "weekday": 3
    },
    "username": "RainbowBatch"
  },
  {
    "oldid": 6408,
    "summary": "RainbowBatch update",
    "time": {
      "date": 1674777600000,
      "day": 27,
      "hour": 1,
      "microsecond": 0,
      "month": 1,
      "second": 10,
      "timezone": "UTC",
      "weekday": 5
    },
    "username": "RainbowBatch"
  },
  {
    "oldid": 6234,
    "summary": "RainbowBatch update",
    "time": {
      "date": 1674432000000,
      "day": 23,
      "hour": 7,
      "microsecond": 0,
      "month": 1,
      "second": 54,
      "timezone": "UTC",
      "weekday": 1
    },
    "username": "RainbowBatch"
  },
  {
    "oldid": 5955,
    "summary": "RainbowBatch update",
    "time": {
      "date": 1673654400000,
      "day": 14,
      "hour": 16,
      "microsecond": 0,
      "month": 1,
      "second": 0,
      "timezone": "UTC",
      "weekday": 6
    },
    "username": "RainbowBatch"
  },
  {
    "oldid": 5940,
    "summary": "Adding categories",
    "time": {
      "date": 1673654400000,
      "day": 14,
      "hour": 3,
      "microsecond": 0,
      "month": 1,
      "second": 31,
      "timezone": "UTC",
      "weekday": 6
    },
    "username": "Woursler"
  },
  {
    "oldid": 5939,
    "summary": "Write a stub.",
    "time": {
      "date": 1673654400000,
      "day": 14,
      "hour": 3,
      "microsecond": 0,
      "month": 1,
      "second": 15,
      "timezone": "UTC",
      "weekday": 6
    },
    "username": "Woursler"
  }
]