[
  {
    "oldid": 4197,
    "summary": "RainbowBatch update",
    "time": {
      "date": 1666742400000,
      "day": 26,
      "hour": 3,
      "microsecond": 0,
      "month": 10,
      "second": 6,
      "timezone": "UTC",
      "weekday": 3
    },
    "username": "RainbowBatch"
  },
  {
    "oldid": 4141,
    "summary": "RainbowBatch update",
    "time": {
      "date": 1666310400000,
      "day": 21,
      "hour": 21,
      "microsecond": 0,
      "month": 10,
      "second": 3,
      "timezone": "UTC",
      "weekday": 5
    },
    "username": "RainbowBatch"
  },
  {
    "oldid": 4109,
    "summary": "RainbowBatch generated stub.",
    "time": {
      "date": 1666310400000,
      "day": 21,
      "hour": 0,
      "microsecond": 0,
      "month": 10,
      "second": 5,
      "timezone": "UTC",
      "weekday": 5
    },
    "username": "RainbowBatch"
  }
]