[
  {
    "oldid": 2420,
    "summary": "RainbowBatch update",
    "time": {
      "date": 1661212800000,
      "day": 23,
      "hour": 17,
      "microsecond": 0,
      "month": 8,
      "second": 40,
      "timezone": "UTC",
      "weekday": 2
    },
    "username": "RainbowBatch"
  },
  {
    "oldid": 457,
    "summary": "Created page with \"{{MessageBox |header     = Notice |text       = We have attempted to make the information contained on this page as objective as possible.  To be clear, this page in no way reflects the opinions of the users or admins of this wiki.  Some information may be sensitive or offensive.  |image      = Wiki.png |imagelink  =  |imagewidth = 50px |id         = warning }}The Protocols of the Elders of Zion (sometimes abbreviated as PEZ) is a wildly anti-semitic forgery. If first ap...\"",
    "time": {
      "date": 1658448000000,
      "day": 22,
      "hour": 23,
      "microsecond": 0,
      "month": 7,
      "second": 34,
      "timezone": "UTC",
      "weekday": 5
    },
    "username": "Woursler"
  }
]